LICENSE
README.md
setup.py
sourceplusplus/SourcePlusPlus.py
sourceplusplus/__init__.py
sourceplusplus.egg-info/PKG-INFO
sourceplusplus.egg-info/SOURCES.txt
sourceplusplus.egg-info/dependency_links.txt
sourceplusplus.egg-info/requires.txt
sourceplusplus.egg-info/top_level.txt
sourceplusplus/control/ContextReceiver.py
sourceplusplus/control/LiveInstrumentRemote.py
sourceplusplus/control/__init__.py
sourceplusplus/models/__init__.py
sourceplusplus/models/command/CommandType.py
sourceplusplus/models/command/LiveInstrumentCommand.py
sourceplusplus/models/command/__init__.py
sourceplusplus/models/instrument/LiveBreakpoint.py
sourceplusplus/models/instrument/LiveLog.py
sourceplusplus/models/instrument/LiveMeter.py
sourceplusplus/models/instrument/LiveSpan.py
sourceplusplus/models/instrument/__init__.py
sourceplusplus/models/instrument/common/LiveInstrument.py
sourceplusplus/models/instrument/common/LiveInstrumentType.py
sourceplusplus/models/instrument/common/LiveSourceLocation.py
sourceplusplus/models/instrument/common/__init__.py
sourceplusplus/models/instrument/common/throttle/HitThrottle.py
sourceplusplus/models/instrument/common/throttle/InstrumentThrottle.py
sourceplusplus/models/instrument/common/throttle/ThrottleStep.py
sourceplusplus/models/instrument/common/throttle/__init__.py
tests/__init__.py
tests/hit_throttle/__init__.py
tests/hit_throttle/tests.py
tests/instrument_expiration/__init__.py
tests/instrument_expiration/tests.py
tests/instrument_serialization/__init__.py
tests/instrument_serialization/tests.py
tests/probe_config/__init__.py
tests/probe_config/tests.py