Metadata-Version: 2.1
Name: sourceplusplus
Version: 0.1.9
Summary: Source++ Python Probe
Home-page: https://github.com/sourceplusplus/probe-python
Author: Source++
Author-email: hello@sourceplus.plus
License: Apache License, Version 2.0
Platform: UNKNOWN
License-File: LICENSE
